pymodaq_plugins_andor/__init__.py
pymodaq_plugins_andor/utils.py
pymodaq_plugins_andor/daq_move_plugins/__init__.py
pymodaq_plugins_andor/daq_move_plugins/daq_move_Shamrock.py
pymodaq_plugins_andor/daq_viewer_plugins/__init__.py
pymodaq_plugins_andor/daq_viewer_plugins/plugins_0D/__init__.py
pymodaq_plugins_andor/daq_viewer_plugins/plugins_1D/__init__.py
pymodaq_plugins_andor/daq_viewer_plugins/plugins_1D/daq_1Dviewer_ShamrockCCD.py
pymodaq_plugins_andor/daq_viewer_plugins/plugins_1D/daq_1Dviewer_ShamrockCCDComposition.py
pymodaq_plugins_andor/daq_viewer_plugins/plugins_1D/daq_1Dviewer_ShamrockSCMOS.py
pymodaq_plugins_andor/daq_viewer_plugins/plugins_1D/daq_1Dviewer_ShamrockSCMOSComposition.py
pymodaq_plugins_andor/daq_viewer_plugins/plugins_2D/__init__.py
pymodaq_plugins_andor/daq_viewer_plugins/plugins_2D/daq_2Dviewer_AndorCCD.py
pymodaq_plugins_andor/daq_viewer_plugins/plugins_2D/daq_2Dviewer_AndorSCMOS.py
pymodaq_plugins_andor/hardware/__init__.py
pymodaq_plugins_andor/hardware/shamrock_sdk.py
pymodaq_plugins_andor/hardware/andor_sdk2/__init__.py
pymodaq_plugins_andor/hardware/andor_sdk2/sdk2.py
pymodaq_plugins_andor/hardware/andor_sdk3/__init__.py
pymodaq_plugins_andor/hardware/andor_sdk3/api.py
pymodaq_plugins_andor/hardware/andor_sdk3/sdk3.py
pymodaq_plugins_andor/hardware/andor_sdk3/sdk3cam.py
pymodaq_plugins_andor/hardware/andor_sdk3/testNeo.py
pymodaq_plugins_andor/resources/__init__.py
pymodaq_plugins_andor/resources/config_template.toml
pymodaq_plugins_andor-5.0.0.dist-info/METADATA
pymodaq_plugins_andor-5.0.0.dist-info/WHEEL
pymodaq_plugins_andor-5.0.0.dist-info/entry_points.txt
pymodaq_plugins_andor-5.0.0.dist-info/licenses/LICENSE
pymodaq_plugins_andor-5.0.0.dist-info/RECORD
